pygotm-0.1.1.data/purelib/pygotm/__init__.py
pygotm-0.1.1.data/purelib/pygotm/python_gotm.dll
pygotm-0.1.1.data/purelib/pygotm/schemas/gotm-3.2.4.schema
pygotm-0.1.1.data/purelib/pygotm/schemas/gotm-3.2.4_gotm-3.3.2.converter
pygotm-0.1.1.data/purelib/pygotm/schemas/gotm-3.3.2.schema
pygotm-0.1.1.data/purelib/pygotm/schemas/gotm-3.3.2_gotm-4.0.0.converter
pygotm-0.1.1.data/purelib/pygotm/schemas/gotm-4.0.0.schema
pygotm-0.1.1.data/purelib/pygotm/schemas/gotm-4.0.0_gotm-5.0.converter
pygotm-0.1.1.data/purelib/pygotm/schemas/gotm-5.0.defaults
pygotm-0.1.1.data/purelib/pygotm/schemas/gotm-5.0.schema
pygotm-0.1.1.data/purelib/pygotm/schemas/gotm-5.0_gotm-5.3.converter
pygotm-0.1.1.data/purelib/pygotm/schemas/gotm-5.3.defaults
pygotm-0.1.1.data/purelib/pygotm/schemas/gotm-5.3.schema
pygotm-0.1.1.dist-info/METADATA
pygotm-0.1.1.dist-info/WHEEL
pygotm-0.1.1.dist-info/top_level.txt
pygotm-0.1.1.dist-info/RECORD
