Metadata-Version: 2.1
Name: pygotm
Version: 0.1.1
Summary: Python wrapper for the General Ocean Turbulence Model
Home-page: UNKNOWN
Author: Jorn Bruggeman
Author-email: jorn@bolding-bruggeman.com
License: GPL
Platform: UNKNOWN
